messenger_logger/__init__.py
messenger_logger/callback.py
messenger_logger_callback-0.1.4.dist-info/METADATA
messenger_logger_callback-0.1.4.dist-info/WHEEL
messenger_logger_callback-0.1.4.dist-info/top_level.txt
messenger_logger_callback-0.1.4.dist-info/RECORD
