Metadata-Version: 2.4
Name: messenger-logger-callback
Version: 0.1.4
Summary: A custom logger and Hugging Face Trainer Callback for sending logs to a remote server with authentication.
Author-email: Riko0 <grigoriyalexeenko@gmail.com>
License: MIT
Project-URL: Homepage, https://github.com/Riko0/messenger-logger-callback
Project-URL: Bug Tracker, https://github.com/Riko0/messenger-logger-callback/issues
Classifier: Programming Language :: Python :: 3
Classifier: Operating System :: OS Independent
Classifier: Topic :: Scientific/Engineering :: Artificial Intelligence
Classifier: Topic :: Software Development :: Libraries :: Python Modules
Requires-Python: >=3.8
Requires-Dist: requests>=2.25.1
Requires-Dist: transformers>=4.0.0
Requires-Dist: python-dotenv>=1.0.0
